testhide_plugin/__init__.py
testhide_plugin/hookspecs.py
testhide_plugin/plugin.py
testhide_pytest_plugin-0.2.7.dist-info/licenses/LICENSE
testhide_pytest_plugin-0.2.7.dist-info/METADATA
testhide_pytest_plugin-0.2.7.dist-info/WHEEL
testhide_pytest_plugin-0.2.7.dist-info/entry_points.txt
testhide_pytest_plugin-0.2.7.dist-info/top_level.txt
testhide_pytest_plugin-0.2.7.dist-info/RECORD
