Metadata-Version: 2.4
Name: testhide-pytest-plugin
Version: 0.2.7
Summary: A pytest plugin for creating incremental XML test reports for Testhide system.
Author-email: Mykola Kovhanko <thuesdays@gmail.com>
License: MIT License
Project-URL: Homepage, https://github.com/thuesdays/testhide-pytest-plugin
Project-URL: Bug Tracker, https://github.com/thuesdays/testhide-pytest-plugin/issues
Classifier: Programming Language :: Python :: 3
Classifier: License :: OSI Approved :: MIT License
Classifier: Operating System :: OS Independent
Classifier: Framework :: Pytest
Requires-Python: >=3.8
License-File: LICENSE
Requires-Dist: pytest>=7.0
Requires-Dist: jira>=3.6.0
Dynamic: license-file
